[
	{
		"__TYPE__": "SharedSliceContent",
		"variation": "default",
		"primary": {
			"image": {
				"origin": {
					"id": "dNN9MbZPuzY",
					"url": "https://images.unsplash.com/photo-1696446700665-1e26fcca574f?crop=entropy&cs=srgb&fm=jpg&ixid=M3wzMzc0NjN8MXwxfHNlYXJjaHwxfHxmcnVpdHxlbnwwfHx8fDE3MDE5NTU0Mzd8MA&ixlib=rb-4.0.3&q=85",
					"width": 6048,
					"height": 4024
				},
				"url": "https://images.unsplash.com/photo-1696446700665-1e26fcca574f?crop=entropy&cs=srgb&fm=jpg&ixid=M3wzMzc0NjN8MXwxfHNlYXJjaHwxfHxmcnVpdHxlbnwwfHx8fDE3MDE5NTU0Mzd8MA&ixlib=rb-4.0.3&q=85",
				"width": 6048,
				"height": 4024,
				"edit": {
					"background": "transparent",
					"zoom": 1,
					"crop": {
						"x": 0,
						"y": 0
					}
				},
				"credits": null,
				"alt": "a man and a woman laying on a blanket with fruit",
				"__TYPE__": "ImageContent",
				"thumbnails": {}
			},
			"copyright": {
				"__TYPE__": "FieldContent",
				"value": "label",
				"type": "Text"
			}
		},
		"items": [
			{
				"__TYPE__": "GroupItemContent",
				"value": []
			}
		]
	},
	{
		"__TYPE__": "SharedSliceContent",
		"variation": "2X",
		"primary": {
			"image": {
				"origin": {
					"id": "main",
					"url": "https://images.unsplash.com/photo-1576662712957-9c79ae1280f8",
					"width": 3456,
					"height": 3456
				},
				"url": "https://images.unsplash.com/photo-1576662712957-9c79ae1280f8",
				"width": 3456,
				"height": 3456,
				"edit": {
					"zoom": 1,
					"crop": {
						"x": 0,
						"y": 0
					},
					"background": "transparent"
				},
				"credits": null,
				"alt": null,
				"__TYPE__": "ImageContent",
				"thumbnails": {}
			},
			"image2": {
				"origin": {
					"id": "main",
					"url": "https://images.unsplash.com/photo-1607582278043-57198ac8da43",
					"width": 4024,
					"height": 4024
				},
				"url": "https://images.unsplash.com/photo-1607582278043-57198ac8da43",
				"width": 4024,
				"height": 4024,
				"edit": {
					"zoom": 1,
					"crop": {
						"x": 0,
						"y": 0
					},
					"background": "transparent"
				},
				"credits": null,
				"alt": null,
				"__TYPE__": "ImageContent",
				"thumbnails": {}
			},
			"copyright": {
				"__TYPE__": "FieldContent",
				"value": "due",
				"type": "Text"
			}
		},
		"items": [
			{
				"__TYPE__": "GroupItemContent",
				"value": []
			}
		]
	},
	{
		"__TYPE__": "SharedSliceContent",
		"variation": "3X",
		"primary": {
			"image": {
				"origin": {
					"id": "main",
					"url": "https://images.unsplash.com/photo-1499951360447-b19be8fe80f5",
					"width": 5848,
					"height": 3899
				},
				"url": "https://images.unsplash.com/photo-1499951360447-b19be8fe80f5",
				"width": 5848,
				"height": 3899,
				"edit": {
					"zoom": 1,
					"crop": {
						"x": 0,
						"y": 0
					},
					"background": "transparent"
				},
				"credits": null,
				"alt": null,
				"__TYPE__": "ImageContent",
				"thumbnails": {}
			},
			"image2": {
				"origin": {
					"id": "main",
					"url": "https://images.unsplash.com/photo-1600861194802-a2b11076bc51",
					"width": 2545,
					"height": 2545
				},
				"url": "https://images.unsplash.com/photo-1600861194802-a2b11076bc51",
				"width": 2545,
				"height": 2545,
				"edit": {
					"zoom": 1,
					"crop": {
						"x": 0,
						"y": 0
					},
					"background": "transparent"
				},
				"credits": null,
				"alt": null,
				"__TYPE__": "ImageContent",
				"thumbnails": {}
			},
			"image3": {
				"origin": {
					"id": "main",
					"url": "https://images.unsplash.com/photo-1493119508027-2b584f234d6c",
					"width": 3424,
					"height": 3424
				},
				"url": "https://images.unsplash.com/photo-1493119508027-2b584f234d6c",
				"width": 3424,
				"height": 3424,
				"edit": {
					"zoom": 1,
					"crop": {
						"x": 0,
						"y": 0
					},
					"background": "transparent"
				},
				"credits": null,
				"alt": null,
				"__TYPE__": "ImageContent",
				"thumbnails": {}
			},
			"copyright": {
				"__TYPE__": "FieldContent",
				"value": "managed",
				"type": "Text"
			}
		},
		"items": [
			{
				"__TYPE__": "GroupItemContent",
				"value": []
			}
		]
	},
	{
		"__TYPE__": "SharedSliceContent",
		"variation": "4X",
		"primary": {
			"image": {
				"origin": {
					"id": "main",
					"url": "https://images.unsplash.com/photo-1587905069134-008460d7a636",
					"width": 3935,
					"height": 5894
				},
				"url": "https://images.unsplash.com/photo-1587905069134-008460d7a636",
				"width": 3935,
				"height": 5894,
				"edit": {
					"zoom": 1,
					"crop": {
						"x": 0,
						"y": 0
					},
					"background": "transparent"
				},
				"credits": null,
				"alt": null,
				"__TYPE__": "ImageContent",
				"thumbnails": {}
			},
			"image2": {
				"origin": {
					"id": "main",
					"url": "https://images.unsplash.com/photo-1493119508027-2b584f234d6c",
					"width": 3424,
					"height": 3424
				},
				"url": "https://images.unsplash.com/photo-1493119508027-2b584f234d6c",
				"width": 3424,
				"height": 3424,
				"edit": {
					"zoom": 1,
					"crop": {
						"x": 0,
						"y": 0
					},
					"background": "transparent"
				},
				"credits": null,
				"alt": null,
				"__TYPE__": "ImageContent",
				"thumbnails": {}
			},
			"image3": {
				"origin": {
					"id": "main",
					"url": "https://images.unsplash.com/photo-1600861194802-a2b11076bc51",
					"width": 2545,
					"height": 2545
				},
				"url": "https://images.unsplash.com/photo-1600861194802-a2b11076bc51",
				"width": 2545,
				"height": 2545,
				"edit": {
					"zoom": 1,
					"crop": {
						"x": 0,
						"y": 0
					},
					"background": "transparent"
				},
				"credits": null,
				"alt": null,
				"__TYPE__": "ImageContent",
				"thumbnails": {}
			},
			"image4": {
				"origin": {
					"id": "main",
					"url": "https://images.unsplash.com/photo-1586952518485-11b180e92764",
					"width": 4172,
					"height": 4000
				},
				"url": "https://images.unsplash.com/photo-1586952518485-11b180e92764",
				"width": 4172,
				"height": 4000,
				"edit": {
					"zoom": 1,
					"crop": {
						"x": 0,
						"y": 0
					},
					"background": "transparent"
				},
				"credits": null,
				"alt": null,
				"__TYPE__": "ImageContent",
				"thumbnails": {}
			},
			"copyright": {
				"__TYPE__": "FieldContent",
				"value": "connected",
				"type": "Text"
			}
		},
		"items": [
			{
				"__TYPE__": "GroupItemContent",
				"value": []
			}
		]
	}
]